LICENSE.txt
README.md
setup.cfg
setup.py
pyResearchInsights/Analyzer.py
pyResearchInsights/Cleaner.py
pyResearchInsights/NLP_Engine.py
pyResearchInsights/Scraper.py
pyResearchInsights/Visualizer.py
pyResearchInsights/__init__.py
pyResearchInsights/common_functions.py
pyResearchInsights/example.py
pyResearchInsights/system_functions.py
pyResearchInsights.egg-info/PKG-INFO
pyResearchInsights.egg-info/SOURCES.txt
pyResearchInsights.egg-info/dependency_links.txt
pyResearchInsights.egg-info/requires.txt
pyResearchInsights.egg-info/top_level.txt